dweetme_client/init.py
dweetme_client-0.0.3.dist-info/licenses/LICENSE
dweetme_client-0.0.3.dist-info/METADATA
dweetme_client-0.0.3.dist-info/WHEEL
dweetme_client-0.0.3.dist-info/top_level.txt
dweetme_client-0.0.3.dist-info/RECORD
